bmpv.py
bmpv-0.1.7.dist-info/METADATA
bmpv-0.1.7.dist-info/WHEEL
bmpv-0.1.7.dist-info/entry_points.txt
bmpv-0.1.7.dist-info/top_level.txt
bmpv-0.1.7.dist-info/RECORD
