Metadata-Version: 2.4
Name: bmpv
Version: 0.1.7
Summary: Add your description here
License-Expression: GPL-3.0-or-later
Project-URL: Homepage, https://github.com/maciakl/bmpv
Project-URL: Issues, https://github.com/maciakl/bmpv/issues
Keywords: version,bump,bumpversion,versioning,automation,tool,cli
Requires-Python: >=3.11
Requires-Dist: pyinstaller>=6.17.0
Requires-Dist: termcolor>=1.1.0
